Registers/4_bit/reg.v
// n-bit register with load

module register
	#(parameter N = 4)
(
	input clk,
	input [N-1:0]I,
	input load,
	output [N-1:0]Q
);
	reg [N-1:0] Q_reg, Q_next;

	always @(posedge clk) begin
		Q_reg <= Q_next;
	end

	always @(I, load) begin
		if(load)
			Q_next = I;
		else
			Q_next = Q_reg;
	end

	assign Q = Q_reg;
endmodule

Registers/4_bit/testbench.v
// Testbench for Register

module testbench();
	parameter N = 4;
	reg clk, load;
	reg [N-1:0]I;
	wire [N-1:0]Q;

	register #(.N(N)) uut1(
		.clk(clk),
		.load(load),
		.I(I),
		.Q(Q)
	);

	localparam T = 20; // clock period

	always begin
		clk = 1'b0; #(T/2)
		clk = 1'b1; #(T/2);
	end

	initial begin
		$dumpfile("reg.vcd");
		$dumpvars(0, testbench);
		
		I = 4'b1011; load = 1'b1; #(T);
		I = 4'b1100; load = 1'b0; #(T);
		I = 4'b0110; load = 1'b1; #(T);
		I = 4'b1001; load = 1'b0; #(T);
		I = 4'b1111; load = 1'b1; #(T);

		$finish;
	end
endmodule

Registers/4_bit/reg.vcd
$date
	Fri Sep 18 11:36:45 2026
$end
$version
	Icarus Verilog
$end
$timescale
	1s
$end
$scope module testbench $end
$var wire 4 ! Q [3:0] $end
$var parameter 32 " N $end
$var parameter 32 # T $end
$var reg 4 $ I [3:0] $end
$var reg 1 % clk $end
$var reg 1 & load $end
$scope module uut1 $end
$var wire 4 ' I [3:0] $end
$var wire 4 ( Q [3:0] $end
$var wire 1 % clk $end
$var wire 1 & load $end
$var parameter 32 ) N $end
$var reg 4 * Q_next [3:0] $end
$var reg 4 + Q_reg [3:0] $end
$upscope $end
$upscope $end
$enddefinitions $end
$comment Show the parameter values. $end
$dumpall
b100 )
b10100 #
b100 "
$end
#0
$dumpvars
bx +
b1011 *
bx (
b1011 '
1&
0%
b1011 $
bx !
$end
#10
b1011 !
b1011 (
b1011 +
1%
#20
0%
0&
b1100 $
b1100 '
#30
1%
#40
b110 *
0%
1&
b110 $
b110 '
#50
b110 !
b110 (
b110 +
1%
#60
0%
0&
b1001 $
b1001 '
#70
1%
#80
b1111 *
0%
1&
b1111 $
b1111 '
#90
b1111 !
b1111 (
b1111 +
1%
