FSM/Mem_Swapper/mem_swapper_fsm.v
// Memory Swapper FSM

module mem_swapper_fsm (
	input clk, reset_n, swap,
	output w,
	output [1:0] select
);
	reg [1:0] state_next, state_reg;
	parameter s0 = 0, s1 = 1, s2 = 2, s3 = 3;

	// State Assignment
	always @(posedge clk) begin
		if (!reset_n)
			state_reg <= 'b0;
		else
			state_reg <= state_next;
	end

	// Next State Logic
	always @(*) begin
		case(state_reg)
			s0: state_next = swap ? s1 : s0;
			s1: state_next = s2;
			s2: state_next = s3;
			s3: state_next = s0;
		endcase
	end

	// Output Logic
	assign w = swap;
	assign select = state_reg;
endmodule

FSM/Mem_Swapper/mux.v
// 4x1 N-Bit MUX

module mux #(parameter N = 4) (
	input [N-1:0] w0, w1, w2, w3,
	input [1:0] sel,
	output reg [N-1:0] Y
);

	always @(*) begin
		Y = 'bx;
		case(sel)
			2'b00: Y = w0;
			2'b01: Y = w1;
			2'b10: Y = w2;
			2'b11: Y = w3;
		endcase
	end	
endmodule

FSM/Mem_Swapper/reg_file.v
// Register

module reg_file #(parameter ADDR_WIDTH = 7, DATA_WIDTH = 8)
(
	input clk,
	input we,
	input [ADDR_WIDTH - 1: 0] addr_w, addr_r,
	input [DATA_WIDTH - 1: 0] data_w,
	output [DATA_WIDTH - 1: 0] data_r
);

	reg [DATA_WIDTH - 1:0] memory [0 : 2**ADDR_WIDTH - 1];

	// Writing into memory
	always @(posedge clk) begin
		if(we)
			memory[addr_w] <= data_w;
	end

	// Reading from memory
	assign data_r = memory[addr_r];

endmodule

FSM/Mem_Swapper/mem_swapper.v
// Memory Swapper

module mem_swapper #(parameter ADDR_WIDTH = 7, DATA_WIDTH = 8) (
	input clk, reset_n, we,
	input [ADDR_WIDTH-1:0] addr_w, addr_r, A, B,
	input [DATA_WIDTH-1:0] data_w,
	input [DATA_WIDTH-1:0] data_r,
	input swap
);
	wire [1:0] sel;
	wire w;
	wire [ADDR_WIDTH - 1: 0]mux_r, mux_w;

	// Register File
	reg_file #(.ADDR_WIDTH(ADDR_WIDTH), .DATA_WIDTH(DATA_WIDTH)) REGFILE (
		.clk(clk),
		.we(w ? 1'b1 : we),
		.addr_w(mux_w),
		.addr_r(mux_r),
		.data_w(w ? data_r : data_w),
		.data_r(data_r)
	);

	// MUX Write
	mux #(.N(ADDR_WIDTH)) MUX_W (
		.w0(addr_w),
		.w1(7'b0),
		.w2(A),
		.w3(B),
		.sel(sel),
		.Y(mux_w)
	);

	// MUX Read
	mux #(.N(ADDR_WIDTH)) MUX_R (
		.w0(addr_r),
		.w1(A),
		.w2(B),
		.w3(7'b0),
		.sel(sel),
		.Y(mux_r)
	);

	// Swapper FSM
	mem_swapper_fsm FSM (
		.clk(clk),
		.reset_n(reset_n),
		.swap(swap),
		.w(w),
		.select(sel)
	);
endmodule

FSM/Mem_Swapper/testbench.v
// Testbench for Memory Swapper
`timescale 1ns/1ps

module testbench();
	
	parameter ADDR_WIDTH = 7, DATA_WIDTH = 8;

	reg clk, reset_n, we, swap;
	reg [ADDR_WIDTH-1 : 0] addr_w, addr_r, A, B;
	reg [DATA_WIDTH-1 : 0] data_w, data_r;

	integer i;

	mem_swapper #(.ADDR_WIDTH(ADDR_WIDTH), .DATA_WIDTH(DATA_WIDTH)) uut1(
		.clk(clk),
		.reset_n(reset_n),
		.we(we),
		.swap(swap),
		.addr_w(addr_w),
		.addr_r(addr_r),
		.A(A),
		.B(B),
		.data_w(data_w),
		.data_r(data_r)
	);

	// Clock
	localparam T = 20;
	always begin
		clk = 1'b0; #(T/2);
		clk = 1'b1; #(T/2);
	end

	initial begin
		$dumpfile("swapper.vcd");
		$dumpvars(0, testbench);

		$dumpvars(1, uut1.REGFILE.memory[19]);
		$dumpvars(1, uut1.REGFILE.memory[20]);
		$dumpvars(1, uut1.REGFILE.memory[21]);
		$dumpvars(1, uut1.REGFILE.memory[25]);
		$dumpvars(1, uut1.REGFILE.memory[26]);
		$dumpvars(1, uut1.REGFILE.memory[27]);

		reset_n = 'b0;
		#2
		swap = 'b0;
		reset_n = 'b1;

		// assigning values at locations 20 thru' 30
		for(i = 20; i < 30; i = i + 1) begin
			@(negedge clk)
			we = 'b1;
			addr_w = i;
			data_w = i;
		end
		
		// Swapping locations 22 and 25
		@(negedge clk)
		swap = 'b1;
		A = 'd22;
		B = 'd25;
		
		repeat(3) @(negedge clk);

		swap = 'b0;

		$finish;
	end
endmodule

FSM/Mem_Swapper/swapper.vcd
$date
	Mon Sep 21 15:19:55 2026
$end
$version
	Icarus Verilog
$end
$timescale
	1ps
$end
$scope module testbench $end
$var parameter 32 ! ADDR_WIDTH $end
$var parameter 32 " DATA_WIDTH $end
$var parameter 32 # T $end
$var reg 7 $ A [6:0] $end
$var reg 7 % B [6:0] $end
$var reg 7 & addr_r [6:0] $end
$var reg 7 ' addr_w [6:0] $end
$var reg 1 ( clk $end
$var reg 8 ) data_r [7:0] $end
$var reg 8 * data_w [7:0] $end
$var reg 1 + reset_n $end
$var reg 1 , swap $end
$var reg 1 - we $end
$var integer 32 . i [31:0] $end
$scope module uut1 $end
$var wire 7 / A [6:0] $end
$var wire 7 0 B [6:0] $end
$var wire 7 1 addr_r [6:0] $end
$var wire 7 2 addr_w [6:0] $end
$var wire 1 ( clk $end
$var wire 8 3 data_r [7:0] $end
$var wire 8 4 data_w [7:0] $end
$var wire 1 + reset_n $end
$var wire 1 , swap $end
$var wire 1 - we $end
$var wire 1 5 w $end
$var wire 2 6 sel [1:0] $end
$var wire 7 7 mux_w [6:0] $end
$var wire 7 8 mux_r [6:0] $end
$var parameter 32 9 ADDR_WIDTH $end
$var parameter 32 : DATA_WIDTH $end
$scope module FSM $end
$var wire 1 ( clk $end
$var wire 1 + reset_n $end
$var wire 2 ; select [1:0] $end
$var wire 1 , swap $end
$var wire 1 5 w $end
$var parameter 32 < s0 $end
$var parameter 32 = s1 $end
$var parameter 32 > s2 $end
$var parameter 32 ? s3 $end
$var reg 2 @ state_next [1:0] $end
$var reg 2 A state_reg [1:0] $end
$upscope $end
$scope module MUX_R $end
$var wire 2 B sel [1:0] $end
$var wire 7 C w0 [6:0] $end
$var wire 7 D w1 [6:0] $end
$var wire 7 E w2 [6:0] $end
$var wire 7 F w3 [6:0] $end
$var parameter 32 G N $end
$var reg 7 H Y [6:0] $end
$upscope $end
$scope module MUX_W $end
$var wire 2 I sel [1:0] $end
$var wire 7 J w0 [6:0] $end
$var wire 7 K w1 [6:0] $end
$var wire 7 L w2 [6:0] $end
$var wire 7 M w3 [6:0] $end
$var parameter 32 N N $end
$var reg 7 O Y [6:0] $end
$upscope $end
$scope module REGFILE $end
$var wire 7 P addr_r [6:0] $end
$var wire 7 Q addr_w [6:0] $end
$var wire 1 ( clk $end
$var wire 8 R data_r [7:0] $end
$var wire 8 S data_w [7:0] $end
$var wire 1 T we $end
$var parameter 32 U ADDR_WIDTH $end
$var parameter 32 V DATA_WIDTH $end
$upscope $end
$upscope $end
$upscope $end
$scope module testbench $end
$scope module uut1 $end
$scope module REGFILE $end
$var reg 8 W \memory[19] [7:0] $end
$upscope $end
$upscope $end
$upscope $end
$scope module testbench $end
$scope module uut1 $end
$scope module REGFILE $end
$var reg 8 X \memory[20] [7:0] $end
$upscope $end
$upscope $end
$upscope $end
$scope module testbench $end
$scope module uut1 $end
$scope module REGFILE $end
$var reg 8 Y \memory[21] [7:0] $end
$upscope $end
$upscope $end
$upscope $end
$scope module testbench $end
$scope module uut1 $end
$scope module REGFILE $end
$var reg 8 Z \memory[25] [7:0] $end
$upscope $end
$upscope $end
$upscope $end
$scope module testbench $end
$scope module uut1 $end
$scope module REGFILE $end
$var reg 8 [ \memory[26] [7:0] $end
$upscope $end
$upscope $end
$upscope $end
$scope module testbench $end
$scope module uut1 $end
$scope module REGFILE $end
$var reg 8 \ \memory[27] [7:0] $end
$upscope $end
$upscope $end
$upscope $end
$enddefinitions $end
$comment Show the parameter values. $end
$dumpall
b1000 V
b111 U
b111 N
b111 G
b11 ?
b10 >
b1 =
b0 <
b1000 :
b111 9
b10100 #
b1000 "
b111 !
$end
#0
$dumpvars
bx \
bx [
bx Z
bx Y
bx X
bx W
xT
bx S
bx R
bx Q
bx P
bx O
bx M
bx L
b0 K
bx J
bx I
bx H
b0 F
bx E
bx D
bx C
bx B
bx A
bx @
bx ;
bx 8
bx 7
bx 6
x5
bx 4
bx 3
bx 2
bx 1
bx 0
bx /
bx .
x-
x,
0+
bx *
bx )
0(
bx '
bx &
bx %
bx $
$end
#2000
b10100 .
1+
05
0,
#10000
1(
#20000
b10100 S
1T
b10101 .
b10100 *
b10100 4
b10100 '
b10100 2
b10100 J
1-
0(
#30000
1(
#40000
b10101 S
b10110 .
b10101 *
b10101 4
b10101 '
b10101 2
b10101 J
0(
#50000
1(
#60000
b10110 S
b10111 .
b10110 *
b10110 4
b10110 '
b10110 2
b10110 J
0(
#70000
1(
#80000
b10111 S
b11000 .
b10111 *
b10111 4
b10111 '
b10111 2
b10111 J
0(
#90000
1(
#100000
b11000 S
b11001 .
b11000 *
b11000 4
b11000 '
b11000 2
b11000 J
0(
#110000
1(
#120000
b11001 S
b11010 .
b11001 *
b11001 4
b11001 '
b11001 2
b11001 J
0(
#130000
1(
#140000
b11010 S
b11011 .
b11010 *
b11010 4
b11010 '
b11010 2
b11010 J
0(
#150000
1(
#160000
b11011 S
b11100 .
b11011 *
b11011 4
b11011 '
b11011 2
b11011 J
0(
#170000
1(
#180000
b11100 S
b11101 .
b11100 *
b11100 4
b11100 '
b11100 2
b11100 J
0(
#190000
1(
#200000
b11101 S
b11110 .
b11101 *
b11101 4
b11101 '
b11101 2
b11101 J
0(
#210000
1(
#220000
bx S
b11001 %
b11001 0
b11001 E
b11001 M
b10110 $
b10110 /
b10110 D
b10110 L
15
1,
0(
#230000
1(
#240000
0(
#250000
1(
#260000
0(
#270000
1(
#280000
b11101 S
05
0,
0(
