Sequential/Sync_Async/D_FF_sync.v
// Synchronous D Flip-Flop

module d_ff_sync (
	input clk,  D,
	input clear_n,
	input preset_n,
	output Q
);	
	reg Q_reg, Q_next;
	
	// Sequential Segment
	always @(posedge clk) begin
		Q_reg <= Q_next;
	end
	
	// Combinational Segment
	always @(D, clear_n, preset_n) begin
		if (!clear_n)
			Q_next = 1'b0;
		else if (!preset_n)
			Q_next = 1'b1;
		else
			Q_next = D;
	end

	assign Q = Q_reg;
endmodule

Sequential/Sync_Async/D_FF_async.v
// Asynchronous D Flip-Flop

module d_ff_async(
	input clk, D,
	input reset_n, // async
	input set_n,
	output Q
);
	reg Q_reg, Q_next;

	// Sequential Segment
	always @(posedge clk, negedge reset_n, negedge set_n) begin
		if(!reset_n)
			Q_reg <= 1'b0;
		else if(!set_n)
			Q_reg <= 1'b1;
		else
			Q_reg <= Q_next;
	end

	// Combinational Segment
	always @(D) begin
		Q_next = D;
	end

	// The combinational segment continuously assigns the value of D to
	// Q_next as D changes, and the sequential segment only assigns that
	// value to Q_reg synchronous to the clock cycle. Hence, to make
	// a parameter synchronous, add it into the Combinational Segment,
	// otherwise into the Sequential Segment
	assign Q = Q_reg;

	// Q is updated only when the next clock cycle starts
endmodule

Sequential/Sync_Async/testbench.v
// Testbench for storage elements

module testbench();
	
	reg clk, D;
	reg set_n, preset_n, clear_n, reset_n;
	wire Q_sync, Q_async;

	d_ff_async uut1(
		.D(D),
		.clk(clk),
		.reset_n(reset_n),
		.set_n(set_n),
		.Q(Q_async)
	);

	d_ff_sync uut2(
		.D(D),
		.clk(clk),
		.preset_n(preset_n),
		.clear_n(clear_n),
		.Q(Q_sync)
	);

	localparam T = 20;		// clock period
	// clock
	always begin
		clk = 1'b0; #(T/2);
		clk = 1'b1; #(T/2);
	end

	initial begin
		$dumpfile("syn_async.vcd");
		$dumpvars(0, testbench);
		
		D = 1'b1;

		reset_n = 0; clear_n = 0; #(T/3)
		reset_n = 1; clear_n = 1;
		set_n = 0; preset_n = 0; #(T/3)
		set_n = 1; preset_n = 1; #(T/3)

		reset_n = 0; clear_n = 0; #(T/3)
		reset_n = 1; clear_n = 1; 
		set_n = 0; preset_n = 0; #(T/3)
		set_n = 1; preset_n = 1; #(T/3)
		
		reset_n = 0; clear_n = 0; #(T/3)
		reset_n = 1; clear_n = 1; 
		set_n = 0; preset_n = 0; #(T/3)
		set_n = 1; preset_n = 1; #(T/3)
	
		$finish;
	end

endmodule

Sequential/Sync_Async/syn_async.vcd
$date
	Fri Sep 18 07:14:04 2026
$end
$version
	Icarus Verilog
$end
$timescale
	1s
$end
$scope module testbench $end
$var wire 1 ! Q_sync $end
$var wire 1 " Q_async $end
$var parameter 32 # T $end
$var reg 1 $ D $end
$var reg 1 % clear_n $end
$var reg 1 & clk $end
$var reg 1 ' preset_n $end
$var reg 1 ( reset_n $end
$var reg 1 ) set_n $end
$scope module uut1 $end
$var wire 1 $ D $end
$var wire 1 " Q $end
$var wire 1 & clk $end
$var wire 1 ( reset_n $end
$var wire 1 ) set_n $end
$var reg 1 * Q_next $end
$var reg 1 + Q_reg $end
$upscope $end
$scope module uut2 $end
$var wire 1 $ D $end
$var wire 1 ! Q $end
$var wire 1 % clear_n $end
$var wire 1 & clk $end
$var wire 1 ' preset_n $end
$var reg 1 , Q_next $end
$var reg 1 - Q_reg $end
$upscope $end
$upscope $end
$enddefinitions $end
$comment Show the parameter values. $end
$dumpall
b10100 #
$end
#0
$dumpvars
x-
0,
0+
1*
x)
0(
x'
0&
0%
1$
0"
x!
$end
#6
1"
1+
1,
0'
0)
1%
1(
#10
1!
1-
1&
#12
1'
1)
#18
0"
0+
0,
0%
0(
#20
0&
#24
1"
1+
1,
0'
0)
1%
1(
#30
1'
1)
1&
#36
0"
0+
0,
0%
0(
#40
0&
#42
1"
1+
1,
0'
0)
1%
1(
#48
1'
1)
