FSM/Seq_Detector/1001_010/melay.v
// Sequence Detector for 1001 & 010 (Melay)

module melay (
	input clk, reset_n,
	input x,
	output y
);
	reg [2:0] state_reg, state_next;

	// States
	localparam s0 = 3'b000;
	localparam s1 = 3'b001;
	localparam s2 = 3'b010;
	localparam s3 = 3'b011;
	localparam s4 = 3'b100;
	localparam s5 = 3'b101;

	// State Register
	always @(posedge clk, negedge reset_n) begin
		if (!reset_n)
			state_reg <= s0;
		else
			state_reg <= state_next;
	end

	// Next State Logic
	always @(*) begin
		case (state_reg)
			s0: state_next = x ? s3 : s1;
			s1: state_next = x ? s2 : s1;
			s2: state_next = x ? s3 : s4;
			s3: state_next = x ? s3 : s4;
			s4: state_next = x ? s2 : s5;
			s5: state_next = x ? s2 : s1;
			default: state_next = s0;
		endcase
	end

	// Output Logic
	assign y = ((state_reg == s5) & x) | ((state_reg == s2) & ~x);
endmodule

FSM/Seq_Detector/1001_010/testbench.v
// Testbench for 1001 & 010 sequence detector
`timescale 1ns/1ps

module testbench();
	reg clk, reset_n;
	reg x;
	wire y;
	
	melay uut1(
		.clk(clk),
		.reset_n(reset_n),
		.x(x),
		.y(y)
	);

	localparam T = 20;
	always begin
		clk = 1'b0; #(T/2);
		clk = 1'b1; #(T/2);
	end

	initial begin
		$dumpfile("sim.vcd");
		$dumpvars(0, testbench);
		
		reset_n = 1'b0;
		x = 1'b0;
		@(negedge clk);
		reset_n = 1'b1;

		#T x = 1'b1;
		#T x = 1'b1;
		#T x = 1'b0;
		#T x = 1'b1;
		#T x = 1'b0;
		#T x = 1'b0;
		#T x = 1'b1;
		#T x = 1'b0;
		#T x = 1'b1;
		#T x = 1'b0;
		#T x = 1'b0;
		#T x = 1'b1;
		#T x = 1'b1;
		#T x = 1'b0;
		#T x = 1'b1;
		#T x = 1'b0;
		#T x = 1'b1;
		#T x = 1'b0;
		#T x = 1'b1;
	
		$finish;
	end
endmodule

FSM/Seq_Detector/1001_010/sim.vcd
$date
	Sun Sep 20 13:30:21 2026
$end
$version
	Icarus Verilog
$end
$timescale
	1ps
$end
$scope module testbench $end
$var wire 1 ! y $end
$var parameter 32 " T $end
$var reg 1 # clk $end
$var reg 1 $ reset_n $end
$var reg 1 % x $end
$scope module uut1 $end
$var wire 1 # clk $end
$var wire 1 $ reset_n $end
$var wire 1 % x $end
$var wire 1 ! y $end
$var parameter 3 & s0 $end
$var parameter 3 ' s1 $end
$var parameter 3 ( s2 $end
$var parameter 3 ) s3 $end
$var parameter 3 * s4 $end
$var parameter 3 + s5 $end
$var reg 3 , state_next [2:0] $end
$var reg 3 - state_reg [2:0] $end
$upscope $end
$upscope $end
$enddefinitions $end
$comment Show the parameter values. $end
$dumpall
b101 +
b100 *
b11 )
b10 (
b1 '
b0 &
b10100 "
$end
#0
$dumpvars
b0 -
b1 ,
0%
0$
0#
0!
$end
#10000
1#
#20000
1$
0#
#30000
b1 -
1#
#40000
b10 ,
0#
1%
#50000
b11 ,
b10 -
1#
#60000
0#
#70000
b11 -
1#
#80000
b100 ,
0#
0%
#90000
b101 ,
b100 -
1#
#100000
b10 ,
0#
1%
#110000
b11 ,
b10 -
1#
#120000
1!
b100 ,
0#
0%
#130000
0!
b101 ,
b100 -
1#
#140000
0#
#150000
b1 ,
b101 -
1#
#160000
1!
b10 ,
0#
1%
#170000
0!
b11 ,
b10 -
1#
#180000
1!
b100 ,
0#
0%
#190000
0!
b101 ,
b100 -
1#
#200000
b10 ,
0#
1%
#210000
b11 ,
b10 -
1#
#220000
1!
b100 ,
0#
0%
#230000
0!
b101 ,
b100 -
1#
#240000
0#
#250000
b1 ,
b101 -
1#
#260000
1!
b10 ,
0#
1%
#270000
0!
b11 ,
b10 -
1#
#280000
0#
#290000
b11 -
1#
#300000
b100 ,
0#
0%
#310000
b101 ,
b100 -
1#
#320000
b10 ,
0#
1%
#330000
b11 ,
b10 -
1#
#340000
1!
b100 ,
0#
0%
#350000
0!
b101 ,
b100 -
1#
#360000
b10 ,
0#
1%
#370000
b11 ,
b10 -
1#
#380000
1!
b100 ,
0#
0%
#390000
0!
b101 ,
b100 -
1#
#400000
b10 ,
0#
1%
