Registers/Shift/usr.v
// Universal Shift Register

module usr
	#(parameter N = 4)
(
	input clk, reset_n,
	input [1:0] s,
	input MSB_in, LSB_in,
	input [N-1:0] I,
	output [N-1:0] Q
);
	reg [N-1:0] Q_reg, Q_next;

	always @(posedge clk, negedge reset_n) begin
		if(!reset_n)
			Q_reg <= 'b0;
		else
			Q_reg <= Q_next;
	end

	// Defining Functionality or Next State Logic
	always @(*) begin
		case (s)
			2'b00: Q_next = Q_reg;
			2'b01: Q_next = {MSB_in, Q_reg[N-1:1]};
			2'b10: Q_next = {Q_reg[N-2:0], LSB_in};
			2'b11: Q_next = I;
			default Q_next = Q_reg;
		endcase
	end

	assign Q = Q_reg;

endmodule

Registers/Shift/testbench.v
// Testbench for USR

module testbench();
	parameter N = 4;
	
	reg clk, reset_n;
	reg [1:0] s;

	reg MSB_in, LSB_in;
	reg [N-1:0] I;

	wire [N-1:0] Q;

	usr #(.N(N)) uut1 (
		.clk(clk),
		.reset_n(reset_n),
		.MSB_in(MSB_in),
		.LSB_in(LSB_in),
		.s(s),
		.I(I),
		.Q(Q)
	);

	// clock
	localparam T = 20;
	always begin
		clk = 1'b0; #(T/2);
		clk = 1'b1; #(T/2);
	end

	initial begin
		$dumpfile("usr.vcd");
		$dumpvars(0, testbench);
		
		// Parallel Load
		s = 2'b11;
		I = 4'b0110; #(T)
		
		// Right Shift
		s = 2'b01;
		MSB_in = 1; #(T)
		MSB_in = 0; #(T)
		MSB_in = 1; #(T)
		MSB_in = 1; #(T)
		
		// Left Shift
		s = 2'b10;
		LSB_in = 1; #(T)
		LSB_in = 0; #(T)
		LSB_in = 1; #(T)
		LSB_in = 0; #(T)

		// Hold
		s = 2'b00; #(3*T/4)	// To observe async behaviour of reset_n

		// Reset
		reset_n = 0; #(T)
		reset_n = 1;

		// Hold
		s = 2'b00; #(T/4)

		// Parallel Load
		s = 2'b11;
		I = 4'b1001; #(T)

		$finish;
	end
endmodule

Registers/Shift/usr.vcd
$date
	Fri Sep 18 12:26:57 2026
$end
$version
	Icarus Verilog
$end
$timescale
	1s
$end
$scope module testbench $end
$var wire 4 ! Q [3:0] $end
$var parameter 32 " N $end
$var parameter 32 # T $end
$var reg 4 $ I [3:0] $end
$var reg 1 % LSB_in $end
$var reg 1 & MSB_in $end
$var reg 1 ' clk $end
$var reg 1 ( reset_n $end
$var reg 2 ) s [1:0] $end
$scope module uut1 $end
$var wire 4 * I [3:0] $end
$var wire 1 % LSB_in $end
$var wire 1 & MSB_in $end
$var wire 4 + Q [3:0] $end
$var wire 1 ' clk $end
$var wire 1 ( reset_n $end
$var wire 2 , s [1:0] $end
$var parameter 32 - N $end
$var reg 4 . Q_next [3:0] $end
$var reg 4 / Q_reg [3:0] $end
$upscope $end
$upscope $end
$enddefinitions $end
$comment Show the parameter values. $end
$dumpall
b100 -
b10100 #
b100 "
$end
#0
$dumpvars
bx /
b110 .
b11 ,
bx +
b110 *
b11 )
x(
0'
x&
x%
b110 $
bx !
$end
#10
b110 !
b110 +
b110 /
1'
#20
b1011 .
0'
1&
b1 )
b1 ,
#30
b1101 .
b1011 !
b1011 +
b1011 /
1'
#40
b101 .
0'
0&
#50
b10 .
b101 !
b101 +
b101 /
1'
#60
b1010 .
0'
1&
#70
b1101 .
b1010 !
b1010 +
b1010 /
1'
#80
0'
#90
b1110 .
b1101 !
b1101 +
b1101 /
1'
#100
b1011 .
0'
1%
b10 )
b10 ,
#110
b111 .
b1011 !
b1011 +
b1011 /
1'
#120
b110 .
0'
0%
#130
b1100 .
b110 !
b110 +
b110 /
1'
#140
b1101 .
0'
1%
#150
b1011 .
b1101 !
b1101 +
b1101 /
1'
#160
b1010 .
0'
0%
#170
b100 .
b1010 !
b1010 +
b1010 /
1'
#180
b1010 .
0'
b0 )
b0 ,
#190
1'
#195
b0 .
b0 !
b0 +
b0 /
0(
#200
0'
#210
1'
#215
1(
#220
b1001 .
b1001 $
b1001 *
b11 )
b11 ,
0'
#230
b1001 !
b1001 +
b1001 /
1'
