Combinational/DEMUX/demux.v
// Module for 1xN DEMUX

module demux
	#(parameter N = 4)
(
	input X,
	input [$clog2(N)-1:0]S,
	output reg [N-1:0]F
);
	integer k;	
	always @(*) begin
		F = 'b0;
		for(k = 0; k < N; k = k + 1) begin
			if(k == S) F[k] = X;
		end
	end
endmodule

Combinational/DEMUX/testbench.v
`timescale 1ns/1ps

module testbench();
	
	parameter N = 6;
	reg X;
	reg [$clog2(N)-1:0]S;
	wire [N-1:0]F;

	demux #(.N(N)) uut1 (
		.X(X),
		.S(S),
		.F(F)
	);

	initial begin
		$dumpfile("demux.vcd");
		$dumpvars(0, testbench);

		X = 1'b1; S = 000; #5
		X = 1'b1; S = 001; #5
		X = 1'b1; S = 010; #5
		X = 1'b1; S = 011; #5
		X = 1'b1; S = 100; #5
		X = 1'b1; S = 101; #5
		X = 1'b1; S = 110; #5
		X = 1'b1; S = 111; #5

		$finish;
	end	
endmodule

Combinational/DEMUX/demux.vcd
$date
	Thu Sep 17 14:57:03 2026
$end
$version
	Icarus Verilog
$end
$timescale
	1ps
$end
$scope module testbench $end
$var wire 6 ! F [5:0] $end
$var parameter 32 " N $end
$var reg 3 # S [2:0] $end
$var reg 1 $ X $end
$scope module uut1 $end
$var wire 3 % S [2:0] $end
$var wire 1 $ X $end
$var parameter 32 & N $end
$var reg 6 ' F [5:0] $end
$var integer 32 ( k [31:0] $end
$upscope $end
$upscope $end
$enddefinitions $end
$comment Show the parameter values. $end
$dumpall
b110 &
b110 "
$end
#0
$dumpvars
b110 (
b1 '
b0 %
1$
b0 #
b1 !
$end
#5000
b110 (
b10 !
b10 '
b1 #
b1 %
#10000
b110 (
b100 !
b100 '
b10 #
b10 %
#15000
b110 (
b1000 !
b1000 '
b11 #
b11 %
#20000
b110 (
b10000 !
b10000 '
b100 #
b100 %
#25000
b110 (
b100000 !
b100000 '
b101 #
b101 %
#30000
b110 (
b0 !
b0 '
b110 #
b110 %
#35000
b110 (
b111 #
b111 %
