FSM/Seq_Detector/101/seq_101_moore.v
// Sequence Detector for 101 (Moore)

module seq_101_moore (
	input clk, reset_n,
	input x,
	output y
);
	reg [1:0] state_reg, state_next;

	localparam s0 = 2'b00;
	localparam s1 = 2'b01;
	localparam s2 = 2'b10;
	localparam s3 = 2'b11;

	// State Register Logic
	always @(posedge clk, negedge reset_n) begin
		if (!reset_n)
			state_reg <= s0;
		else
			state_reg <= state_next;
	end

	// Next State Logic
	always @(*) begin
		case (state_reg)
			s0: state_next = x ? s1 : s0;
			s1: state_next = x ? s1 : s2;
			s2: state_next = x ? s3 : s0;
			s3: state_next = x ? s1 : s2;
			default: state_next = state_reg;
		endcase
	end

	// Output Logic
	assign y = (state_reg == s3);
endmodule

FSM/Seq_Detector/101/seq_101_melay.v
// Sequence Detector for 101 (Melay)

module seq_101_melay (
	input clk, reset_n,
	input x,
	output y
);
	reg [1:0] state_reg, state_next;

	// States
	localparam s0 = 2'b00;
	localparam s1 = 2'b01;
	localparam s2 = 2'b10;

	// State Register
	always @(posedge clk, negedge reset_n) begin
		if (!reset_n)
			state_reg <= s0;
		else
			state_reg <= state_next;
	end

	// Next State Logic
	always @(*) begin
		case (state_reg)
			s0: state_next = x ? s1 : s0;
			s1: state_next = x ? s1 : s2;
			s2: state_next = x ? s1 : s0;
			default: state_next = s0;
		endcase
	end

	// Output Logic
	assign y = (state_reg == s2) & x;	// when S2 receives input x = 1
endmodule

FSM/Seq_Detector/101/testbench.v
// Testbench for 101 sequence detector
`timescale 1ns/1ps

module testbench();
	reg clk, reset_n;
	reg x;
	wire y_melay, y_moore;
	
	seq_101_melay uut1(
		.clk(clk),
		.reset_n(reset_n),
		.x(x),
		.y(y_melay)
	);

	seq_101_moore uut2(
		.clk(clk),
		.reset_n(reset_n),
		.x(x),
		.y(y_moore)
	);

	localparam T = 20;
	always begin
		clk = 1'b0; #(T/2);
		clk = 1'b1; #(T/2);
	end

	initial begin
		$dumpfile("seq_101.vcd");
		$dumpvars(0, testbench);
		
		reset_n = 1'b0;
		x = 1'b0;
		@(negedge clk);
		reset_n = 1'b1;

		#T x = 1'b1;
		#T x = 1'b1;
		#T x = 1'b0;
		#T x = 1'b1;
		#T x = 1'b0;
		#T x = 1'b0;
		#T x = 1'b0;
		#T x = 1'b1;
		#T x = 1'b0;
		#T x = 1'b1;
		#T x = 1'b0;
		#T x = 1'b1;
		#T x = 1'b1;
		#T x = 1'b0;
		#T x = 1'b1;
		#T x = 1'b0;
		#T x = 1'b1;
		#T x = 1'b0;
		#T x = 1'b1;
	
		$finish;
	end
endmodule

FSM/Seq_Detector/101/seq_101.vcd
$date
	Sat Sep 19 23:11:36 2026
$end
$version
	Icarus Verilog
$end
$timescale
	1ps
$end
$scope module testbench $end
$var wire 1 ! y_moore $end
$var wire 1 " y_melay $end
$var parameter 32 # T $end
$var reg 1 $ clk $end
$var reg 1 % reset_n $end
$var reg 1 & x $end
$scope module uut1 $end
$var wire 1 $ clk $end
$var wire 1 % reset_n $end
$var wire 1 & x $end
$var wire 1 " y $end
$var parameter 2 ' s0 $end
$var parameter 2 ( s1 $end
$var parameter 2 ) s2 $end
$var reg 2 * state_next [1:0] $end
$var reg 2 + state_reg [1:0] $end
$upscope $end
$scope module uut2 $end
$var wire 1 $ clk $end
$var wire 1 % reset_n $end
$var wire 1 & x $end
$var wire 1 ! y $end
$var parameter 2 , s0 $end
$var parameter 2 - s1 $end
$var parameter 2 . s2 $end
$var parameter 2 / s3 $end
$var reg 2 0 state_next [1:0] $end
$var reg 2 1 state_reg [1:0] $end
$upscope $end
$upscope $end
$enddefinitions $end
$comment Show the parameter values. $end
$dumpall
b11 /
b10 .
b1 -
b0 ,
b10 )
b1 (
b0 '
b10100 #
$end
#0
$dumpvars
b0 1
b0 0
b0 +
b0 *
0&
0%
0$
0"
0!
$end
#10000
1$
#20000
1%
0$
#30000
1$
#40000
b1 *
b1 0
0$
1&
#50000
b1 1
b1 +
1$
#60000
0$
#70000
1$
#80000
b10 *
b10 0
0$
0&
#90000
b0 0
b0 *
b10 1
b10 +
1$
#100000
1"
b1 *
b11 0
0$
1&
#110000
0"
b1 0
b1 +
1!
b11 1
1$
#120000
b10 *
b10 0
0$
0&
#130000
b0 0
b0 *
0!
b10 1
b10 +
1$
#140000
0$
#150000
b0 +
b0 1
1$
#160000
0$
#170000
1$
#180000
b1 *
b1 0
0$
1&
#190000
b1 +
b1 1
1$
#200000
b10 *
b10 0
0$
0&
#210000
b0 0
b0 *
b10 1
b10 +
1$
#220000
1"
b1 *
b11 0
0$
1&
#230000
0"
b1 0
b1 +
1!
b11 1
1$
#240000
b10 *
b10 0
0$
0&
#250000
b0 0
b0 *
0!
b10 1
b10 +
1$
#260000
1"
b1 *
b11 0
0$
1&
#270000
0"
b1 0
b1 +
1!
b11 1
1$
#280000
0$
#290000
0!
b1 1
1$
#300000
b10 *
b10 0
0$
0&
#310000
b0 *
b0 0
b10 +
b10 1
1$
#320000
1"
b1 *
b11 0
0$
1&
#330000
b1 0
0"
1!
b11 1
b1 +
1$
#340000
b10 *
b10 0
0$
0&
#350000
b0 *
b0 0
b10 +
0!
b10 1
1$
#360000
1"
b1 *
b11 0
0$
1&
#370000
b1 0
0"
1!
b11 1
b1 +
1$
#380000
b10 *
b10 0
0$
0&
#390000
b0 *
b0 0
b10 +
0!
b10 1
1$
#400000
1"
b1 *
b11 0
0$
1&
