Combinational/MUX/mux.v
// Module for 1-bit NX1 multiplexer

module mux
	#(parameter N = 4)
(
	input [N-1:0]X,
	input [$clog2(N) - 1: 0]S,
	output reg F
);
	integer k;

	always @(*) begin
		F = 'bx;
		for(k = 0; k < N; k = k + 1) begin
			if(k == S) F = X[k];
		end
	end

endmodule

Combinational/MUX/testbench.v
`timescale 1ns/1ps

module testbench();
	
	parameter N = 6;
	reg [N-1:0]X;
	reg [$clog2(N)-1:0]S;
	wire F;

	mux #(.N(N)) uut1 (
		.X(X),
		.S(S),
		.F(F)
	);

	initial begin
		$dumpfile("mux.vcd");
		$dumpvars(0, testbench);

		X = 6'b101001; S = 000; #5
		X = 6'b101001; S = 001; #5
		X = 6'b101001; S = 010; #5
		X = 6'b101001; S = 011; #5
		X = 6'b101001; S = 100; #5
		X = 6'b101001; S = 101; #5
		X = 6'b101001; S = 110; #5
		X = 6'b101001; S = 111; #5

		$finish;
	end	
endmodule

Combinational/MUX/mux.vcd
$date
	Thu Sep 17 14:09:11 2026
$end
$version
	Icarus Verilog
$end
$timescale
	1ps
$end
$scope module testbench $end
$var wire 1 ! F $end
$var parameter 32 " N $end
$var reg 3 # S [2:0] $end
$var reg 6 $ X [5:0] $end
$scope module uut1 $end
$var wire 3 % S [2:0] $end
$var wire 6 & X [5:0] $end
$var parameter 32 ' N $end
$var reg 1 ! F $end
$var integer 32 ( k [31:0] $end
$upscope $end
$upscope $end
$enddefinitions $end
$comment Show the parameter values. $end
$dumpall
b110 '
b110 "
$end
#0
$dumpvars
b110 (
b101001 &
b0 %
b101001 $
b0 #
1!
$end
#5000
b110 (
0!
b1 #
b1 %
#10000
b110 (
0!
b10 #
b10 %
#15000
b110 (
1!
b11 #
b11 %
#20000
b110 (
0!
b100 #
b100 %
#25000
b110 (
1!
b101 #
b101 %
#30000
b110 (
x!
b110 #
b110 %
#35000
b110 (
b111 #
b111 %
