Arithmetic/Adders/adder.v
module adder(
	input wire A,  B,
	output reg S, Co
);
	always @(A,B) begin
		S = A ^ B;
		Co = A & B;
	end
endmodule

Arithmetic/Adders/full_adder.v
module full_adder(
	input wire A, B, Ci,
	output S, Co // changed from reg to wire since reg can only be assigned in always or initial blocks
);
	wire s1, c1, c2;

	adder uut1(
		.A(A), .B(B), .S(s1), .Co(c1)
	);
		
	adder uut2(
		.A(Ci), .B(s1), .S(S), .Co(c2)
	);	// output S is a wire which cannot be assigned to reg S of current module since outside
	
	assign Co = c1 | c2;

endmodule

Arithmetic/Adders/full_adder_tb.v
`timescale 1ns/1ps

module full_adder_tb;

	reg A, B, Ci;
	wire S, Co;

	full_adder uut(
		.A(A), .B(B), .Ci(Ci),
		.S(S), .Co(Co)
	);
	
	initial begin
		$dumpfile("full_adder.vcd");
		$dumpvars(0, full_adder_tb);

		A = 0; B = 0; Ci = 0; #10
		A = 0; B = 0; Ci = 1; #10
		A = 0; B = 1; Ci = 0; #10
		A = 0; B = 1; Ci = 1; #10
		A = 1; B = 0; Ci = 0; #10
		A = 1; B = 0; Ci = 1; #10
		A = 1; B = 1; Ci = 0; #10
		A = 1; B = 1; Ci = 1; #10
		
		$finish;
	end
endmodule

Arithmetic/Adders/.gitignore/full_adder.vcd
$date
	Thu Sep 10 21:37:51 2026
$end
$version
	Icarus Verilog
$end
$timescale
	1ps
$end
$scope module full_adder_tb $end
$var wire 1 ! S $end
$var wire 1 " Co $end
$var reg 1 # A $end
$var reg 1 $ B $end
$var reg 1 % Ci $end
$scope module uut $end
$var wire 1 # A $end
$var wire 1 $ B $end
$var wire 1 % Ci $end
$var wire 1 " Co $end
$var wire 1 & s1 $end
$var wire 1 ' c2 $end
$var wire 1 ( c1 $end
$var wire 1 ! S $end
$scope module uut1 $end
$var wire 1 # A $end
$var wire 1 $ B $end
$var reg 1 ( Co $end
$var reg 1 & S $end
$upscope $end
$scope module uut2 $end
$var wire 1 % A $end
$var wire 1 & B $end
$var reg 1 ' Co $end
$var reg 1 ! S $end
$upscope $end
$upscope $end
$upscope $end
$enddefinitions $end
$comment Show the parameter values. $end
$dumpall
$end
#0
$dumpvars
0(
0'
0&
0%
0$
0#
0"
0!
$end
#10000
1!
1%
#20000
1&
0%
1$
#30000
1"
1'
0!
1%
#40000
0"
0'
1!
0%
0$
1#
#50000
1"
1'
0!
1%
#60000
0'
1(
0&
0%
1$
#70000
1!
1%
