Combinational/ENCODER/enc.v
// Module for 2n x n Priority Encoder

module pr_enc
	#(parameter N = 4)
(
	input [N-1:0]I,
	input en,
	output reg [$clog2(N)-1:0]Y
);
	integer k;

	always @(I, en) begin
		Y = 'bx;
		if (en)
			for(k = 0; k < N; k = k + 1) begin
				if(I[k])
					Y = k;				
			end
	end
endmodule

Combinational/ENCODER/testbench.v
`timescale 1ns/1ps

module testbench();
	parameter N = 4;
	reg [N-1:0]I;
	reg en;
	wire [$clog2(N)-1:0]Y;

	pr_enc #(.N(N)) uut1 (
		.I(I),
		.en(en),
		.Y(Y)
	);

	initial begin
		$dumpfile("priority_encoder.vcd");
		$dumpvars(0, testbench);
		
		en = 0;

		I = 4'b0001;	#5
		I = 4'b0010;	#5
		I = 4'b1000;	#5
		I = 4'b1001;	#5

		en = 1;

		I = 4'b0001;	#5
		I = 4'b0010;	#5
		I = 4'b1000;	#5
		I = 4'b1001;	#5
		
		$finish;
	end
endmodule

Combinational/ENCODER/priority_encoder.vcd
$date
	Thu Sep 17 15:20:18 2026
$end
$version
	Icarus Verilog
$end
$timescale
	1ps
$end
$scope module testbench $end
$var wire 2 ! Y [1:0] $end
$var parameter 32 " N $end
$var reg 4 # I [3:0] $end
$var reg 1 $ en $end
$scope module uut1 $end
$var wire 4 % I [3:0] $end
$var wire 1 $ en $end
$var parameter 32 & N $end
$var reg 2 ' Y [1:0] $end
$var integer 32 ( k [31:0] $end
$upscope $end
$upscope $end
$enddefinitions $end
$comment Show the parameter values. $end
$dumpall
b100 &
b100 "
$end
#0
$dumpvars
bx (
bx '
b1 %
0$
b1 #
bx !
$end
#5000
b10 #
b10 %
#10000
b1000 #
b1000 %
#15000
b1001 #
b1001 %
#20000
b0 !
b0 '
b100 (
b1 #
b1 %
1$
#25000
b100 (
b1 !
b1 '
b10 #
b10 %
#30000
b100 (
b11 !
b11 '
b1000 #
b1000 %
#35000
b100 (
b11 !
b11 '
b1001 #
b1001 %
