Sequential/Storage_Elements/D_FF_pos.v
// Negitive-edge trigerred D-FF

module D_FF_pos(
	input clk, D,
	output reg Q,
	output Q_b
);
	assign Q_b = ~Q;

	always @(posedge clk) begin
		Q <= D;
	end

endmodule

Sequential/Storage_Elements/D_FF_neg.v
// Negitive-edge trigerred D-FF

module D_FF_neg(
	input clk, D,
	output Q_b,
	output reg Q
);
	assign Q_b = ~Q;

	always @(negedge clk) begin
		Q <= D;
	end

endmodule

Sequential/Storage_Elements/D_Latch.v
// Module for D-Latch

module D_Latch(
	input D, clk,
	output reg Q,
	output Q_b
);
	assign Q_b = ~Q;

	always @(D, clk) begin
		if(clk) Q <= D;
		else Q <= Q;
	end
endmodule

Sequential/Storage_Elements/stgels.v
// Module covering all storage elements for simulation

module stgels(
	input clk, D,
	output Q_latch, Q_neg, Q_pos
);
	D_Latch d_l(
		.D(D),
		.clk(clk),
		.Q(Q_latch)
	);

	D_FF_neg d_fn(
		.D(D),
		.clk(clk),
		.Q(Q_neg)
	);

	D_FF_pos d_fp(
		.D(D),
		.clk(clk),
		.Q(Q_pos)
	);

endmodule

Sequential/Storage_Elements/stgels_tb.v
// Testbench for storage elements

module testbench();
	
	reg clk, D;
	wire Q_latch, Q_neg, Q_pos;

	stgels uut1(
		.D(D),
		.clk(clk),
		.Q_latch(Q_latch),
		.Q_neg(Q_neg),
		.Q_pos(Q_pos)
	);

	localparam T = 20;		// clock period
	// clock
	always begin
		clk = 1'b0; #(T/2);
		clk = 1'b1; #(T/2);
	end

	initial begin
		$dumpfile("stgels.vcd");
		$dumpvars(0, testbench);
		
		D = 1'b0; #(2*T)
		D = 1'b1; #(2*T)

		@(posedge clk);			
		D = 1'b0; #2
		D = 1'b1; #3
		D = 1'b0; #4
		D = 1'b1; #4

		@(negedge clk);			
		D = 1'b0; #2
		D = 1'b1; #3
		D = 1'b0; #4
		D = 1'b1; #4
		
		$finish;
	end

endmodule

Sequential/Storage_Elements/stgels.vcd
$date
	Thu Sep 17 16:13:21 2026
$end
$version
	Icarus Verilog
$end
$timescale
	1s
$end
$scope module testbench $end
$var wire 1 ! Q_pos $end
$var wire 1 " Q_neg $end
$var wire 1 # Q_latch $end
$var parameter 32 $ T $end
$var reg 1 % D $end
$var reg 1 & clk $end
$scope module uut1 $end
$var wire 1 % D $end
$var wire 1 & clk $end
$var wire 1 ! Q_pos $end
$var wire 1 " Q_neg $end
$var wire 1 # Q_latch $end
$scope module d_fn $end
$var wire 1 % D $end
$var wire 1 ' Q_b $end
$var wire 1 & clk $end
$var reg 1 " Q $end
$upscope $end
$scope module d_fp $end
$var wire 1 % D $end
$var wire 1 ( Q_b $end
$var wire 1 & clk $end
$var reg 1 ! Q $end
$upscope $end
$scope module d_l $end
$var wire 1 % D $end
$var wire 1 ) Q_b $end
$var wire 1 & clk $end
$var reg 1 # Q $end
$upscope $end
$upscope $end
$upscope $end
$enddefinitions $end
$comment Show the parameter values. $end
$dumpall
b10100 $
$end
#0
$dumpvars
x)
x(
1'
0&
0%
x#
0"
x!
$end
#10
1(
1)
0!
0#
1&
#20
0&
#30
1&
#40
0'
1"
0&
1%
#50
0(
0)
1!
1#
1&
#60
0&
#70
1&
#80
0&
#90
1)
1(
0#
0!
0%
1&
#92
0)
1#
1%
#95
1)
0#
0%
#99
0)
1#
1%
#100
0&
#110
0(
1!
1&
#120
1'
0"
0%
0&
#122
1%
#125
0%
#129
1%
